compas_rrc/__init__.py
compas_rrc/__install.py
compas_rrc/__version__.py
compas_rrc/client.py
compas_rrc/common.py
compas_rrc/custom.py
compas_rrc/io.py
compas_rrc/motion.py
compas_rrc/msg.py
compas_rrc/utility.py
compas_rrc/watch.py
compas_rrc-2.0.0.dist-info/AUTHORS.rst
compas_rrc-2.0.0.dist-info/LICENSE
compas_rrc-2.0.0.dist-info/METADATA
compas_rrc-2.0.0.dist-info/WHEEL
compas_rrc-2.0.0.dist-info/top_level.txt
compas_rrc-2.0.0.dist-info/RECORD
